jaxed/__init__.py
jaxed-0.0.1.dist-info/METADATA
jaxed-0.0.1.dist-info/WHEEL
jaxed-0.0.1.dist-info/top_level.txt
jaxed-0.0.1.dist-info/RECORD
